server/__init__.py
server/decos.py
server/descriptors.py
server/errors.py
server/metaclass.py
server/server_gui.py
server/server_run.py
server/common/__init__.py
server/common/errors.py
server/common/utils.py
server/common/variables.py
server/database/__init__.py
server/database/server_db.py
server/logs/__init__.py
server/logs/client_log_config.py
server/logs/server_log_config.py
server/server/__init__.py
server/server/add_user.py
server/server/config_window.py
server/server/core.py
server/server/main_window.py
server/server/remove_user.py
server/server/stat_window.py
server/unit_tests/__init__.py
server/unit_tests/test_client.py
server/unit_tests/test_server.py
server/unit_tests/test_utils.py
kodo_messenger_server-0.0.4.dist-info/METADATA
kodo_messenger_server-0.0.4.dist-info/WHEEL
kodo_messenger_server-0.0.4.dist-info/top_level.txt
kodo_messenger_server-0.0.4.dist-info/RECORD
