Metadata-Version: 2.1
Name: kodo-messenger-server
Version: 0.0.4
Summary: kodo_messenger_server
Home-page: UNKNOWN
Author: Roman Kodoch
Author-email: kodochigovra@mail.ru
License: UNKNOWN
Platform: UNKNOWN
Requires-Dist: PyQt5
Requires-Dist: sqlalchemy
